odoo/addons/web_widget_section_and_note_text_scrollable/README.rst
odoo/addons/web_widget_section_and_note_text_scrollable/__init__.py
odoo/addons/web_widget_section_and_note_text_scrollable/__manifest__.py
odoo/addons/web_widget_section_and_note_text_scrollable/i18n/it.po
odoo/addons/web_widget_section_and_note_text_scrollable/i18n/web_widget_section_and_note_text_scrollable.pot
odoo/addons/web_widget_section_and_note_text_scrollable/readme/CONTRIBUTORS.md
odoo/addons/web_widget_section_and_note_text_scrollable/readme/DESCRIPTION.md
odoo/addons/web_widget_section_and_note_text_scrollable/static/description/icon.png
odoo/addons/web_widget_section_and_note_text_scrollable/static/description/index.html
odoo/addons/web_widget_section_and_note_text_scrollable/static/description/scroll_line_description.gif
odoo/addons/web_widget_section_and_note_text_scrollable/static/description/scroll_note.gif
odoo/addons/web_widget_section_and_note_text_scrollable/static/src/section_and_note_text_scrollable.scss
odoo_addon_web_widget_section_and_note_text_scrollable-17.0.1.0.0.3.dist-info/METADATA
odoo_addon_web_widget_section_and_note_text_scrollable-17.0.1.0.0.3.dist-info/WHEEL
odoo_addon_web_widget_section_and_note_text_scrollable-17.0.1.0.0.3.dist-info/top_level.txt
odoo_addon_web_widget_section_and_note_text_scrollable-17.0.1.0.0.3.dist-info/RECORD
